{"cameraMode":{"drawMode":0,"name":"Shaded","section":"Shading Mode"},"sceneLighting":false,"audioPlay":false,"sceneViewState":{"m_AlwaysRefresh":false,"showFog":true,"showSkybox":false,"showFlares":true,"showImageEffects":true,"showParticleSystems":true,"showVisualEffectGraphs":true,"m_FxEnabled":true},"in2DMode":false,"pivot":{"x":8.40000057220459,"y":1.0407719612121583,"z":12.059563636779786},"rotation":{"x":-0.08433028310537338,"y":-0.8333704471588135,"z":0.13261546194553376,"w":-0.5299311876296997},"size":6.889101505279541,"orthographic":false}